LICENSE.txt
MANIFEST.in
README.md
setup.cfg
setup.py
mezzanine_people/__init__.py
mezzanine_people/admin.py
mezzanine_people/defaults.py
mezzanine_people/models.py
mezzanine_people/tests.py
mezzanine_people/urls.py
mezzanine_people/views.py
mezzanine_people.egg-info/PKG-INFO
mezzanine_people.egg-info/SOURCES.txt
mezzanine_people.egg-info/dependency_links.txt
mezzanine_people.egg-info/top_level.txt
mezzanine_people/migrations/0001_initial.py
mezzanine_people/migrations/0001_initial.pyc
mezzanine_people/migrations/__init__.py
mezzanine_people/migrations/__init__.pyc
mezzanine_people/templates/mezzanine_people/person_detail.html
mezzanine_people/templates/mezzanine_people/person_list.html
mezzanine_people/templatetags/__init__.py
mezzanine_people/templatetags/__init__.pyc
mezzanine_people/templatetags/people_tags.py