Metadata-Version: 1.1
Name: mezzanine-people
Version: 0.1
Summary: A simple People app for Mezzanine CMS sites.
Home-page: https://github.com/eci/mezzanine-people
Author: Doug Evenhouse
Author-email: doug.evenhouse@gmail.com
License: MIT License
Platform: UNKNOWN
Classifier: Environment :: Web Environment
Classifier: Framework :: Django
Classifier: Intended Audience :: Developers
Classifier: License :: OSI Approved :: MIT License
Classifier: Operating System :: OS Independent
Classifier: Programming Language :: Python
Classifier: Topic :: Internet :: WWW/HTTP
Classifier: Topic :: Internet :: WWW/HTTP :: Dynamic Content
